clanker_score/__init__.py
clanker_score/ddg_results_by_kwd_density.py
clanker_score/ddg_results_by_kwd_density.py~
clanker_score/keyword_density.py
clanker_score/keyword_density.py~
clanker_score/Obsolete/clanker_score_main.py
clanker_score/Obsolete/clanker_score_main.py~
clanker_score/Obsolete/clanker_score_main.scikit
clanker_score-0.1.5.data/data/Horst_von_Harbou_-_Metropolis_set_photograph_09.jpg
clanker_score-0.1.5.data/data/Horst_von_Harbou_-_Metropolis_set_photograph_09.provenance
clanker_score-0.1.5.dist-info/entry_points.txt
clanker_score-0.1.5.dist-info/licenses/LICENSE
clanker_score-0.1.5.dist-info/WHEEL
clanker_score-0.1.5.dist-info/METADATA
clanker_score-0.1.5.dist-info/RECORD
