Metadata-Version: 2.4
Name: clanker_score
Version: 0.1.5
Summary: clanker_score rates search results by keyword density.
Keywords: keyword density,keyword frequency,search results,keyword stuffing,clanker,AI detection,SEO
Author-email: Chuck Rhode <CRhode@LacusVeris.com>
Requires-Python: >=3.11
Classifier: License :: OSI Approved :: GNU General Public License v3 or later (GPLv3+)
Classifier: Development Status :: 3 - Alpha
Classifier: Environment :: Console
Classifier: Intended Audience :: End Users/Desktop
Classifier: Natural Language :: English
Classifier: Operating System :: Microsoft :: Windows
Classifier: Operating System :: Unix
Classifier: Programming Language :: Python :: 3
Classifier: Topic :: Utilities
License-File: LICENSE
Requires-Dist: lxml
Requires-Dist: bs4
Requires-Dist: nltk
Project-URL: Home, https://LacusVeris.com/ClankerScoreDocs
